Metadata-Version: 1.1
Name: ezread
Version: 0.0.1
Summary: ezread provides a ridiculously simple way to fetch items within the JSON list.
Home-page: https://github.com/csurfer/ezread
Author: Vishwas B Sharma
Author-email: sharma.vishwas88@gmail.com
License: MIT
Keywords: python json csv
Platform: UNKNOWN
Classifier: Intended Audience :: Developers
Classifier: Intended Audience :: Education
Classifier: License :: OSI Approved :: MIT License
Classifier: Development Status :: 3 - Alpha
Classifier: Operating System :: POSIX
Classifier: Programming Language :: Python :: 3.6
Classifier: Programming Language :: Python :: 3.7
Classifier: Topic :: Software Development :: Build Tools
Classifier: Topic :: Software Development :: Libraries :: Python Modules
